<annotation>
	<folder>mydata</folder>
	<filename>IMG_5284.jpg</filename>
	<path>/Users/chintu/Desktop/mydata/IMG_5284.jpg</path>
	<source>
		<database>Unknown</database>
	</source>
	<size>
		<width>3024</width>
		<height>4032</height>
		<depth>3</depth>
	</size>
	<segmented>0</segmented>
	<object>
		<name>finger</name>
		<pose>Unspecified</pose>
		<truncated>0</truncated>
		<difficult>0</difficult>
		<bndbox>
			<xmin>552</xmin>
			<ymin>766</ymin>
			<xmax>976</xmax>
			<ymax>1156</ymax>
		</bndbox>
	</object>
	<object>
		<name>finger</name>
		<pose>Unspecified</pose>
		<truncated>0</truncated>
		<difficult>0</difficult>
		<bndbox>
			<xmin>72</xmin>
			<ymin>1102</ymin>
			<xmax>562</xmax>
			<ymax>1466</ymax>
		</bndbox>
	</object>
	<object>
		<name>finger</name>
		<pose>Unspecified</pose>
		<truncated>0</truncated>
		<difficult>0</difficult>
		<bndbox>
			<xmin>53</xmin>
			<ymin>1582</ymin>
			<xmax>483</xmax>
			<ymax>1932</ymax>
		</bndbox>
	</object>
	<object>
		<name>finger</name>
		<pose>Unspecified</pose>
		<truncated>0</truncated>
		<difficult>0</difficult>
		<bndbox>
			<xmin>173</xmin>
			<ymin>2149</ymin>
			<xmax>597</xmax>
			<ymax>2492</ymax>
		</bndbox>
	</object>
	<object>
		<name>finger</name>
		<pose>Unspecified</pose>
		<truncated>0</truncated>
		<difficult>0</difficult>
		<bndbox>
			<xmin>2052</xmin>
			<ymin>804</ymin>
			<xmax>2449</xmax>
			<ymax>1374</ymax>
		</bndbox>
	</object>
</annotation>
